s2opy-0.1.0.dist-info/METADATA
s2opy-0.1.0.dist-info/WHEEL
s2opy/__init__.py
s2opy/s2opy.cpython-312-darwin.so
s2opy-0.1.0.dist-info/RECORD
