Metadata-Version: 2.1
Name: s2opy
Version: 0.1.0
Requires-Python: >=3.7
